{
  "type": "FeatureCollection",
  "features": [
    {
      "type": "Feature",
      "properties": {},
      "geometry": {
        "coordinates": [
          74.58619723703637,
          42.844042032882356
        ],
        "type": "Point"
      }
    },
    {
      "type": "Feature",
      "properties": {},
      "geometry": {
        "coordinates": [
          74.58643798274542,
          42.84882689465405
        ],
        "type": "Point"
      }
    },
    {
      "type": "Feature",
      "properties": {},
      "geometry": {
        "coordinates": [
          74.58674319573569,
          42.85420235369878
        ],
        "type": "Point"
      }
    },
    {
      "type": "Feature",
      "properties": {},
      "geometry": {
        "coordinates": [
          74.58711701948812,
          42.8602527925853
        ],
        "type": "Point"
      }
    },
    {
      "type": "Feature",
      "properties": {},
      "geometry": {
        "coordinates": [
          74.58767171112584,
          42.86801979095915
        ],
        "type": "Point"
      }
    },
    {
      "type": "Feature",
      "properties": {},
      "geometry": {
        "coordinates": [
          74.58808305491826,
          42.873147454398634
        ],
        "type": "Point"
      }
    }
  ]
}